{"data":{"allGoogleSpreadsheetCategories":{"edges":[{"node":{"categoryName":"Health care\n","iconId":"capsules","categorySlug":"health-care"}},{"node":{"categoryName":"Marijuana","iconId":"cannabis","categorySlug":"marijuana"}},{"node":{"categoryName":"Public Lands","iconId":"mountain","categorySlug":"public-lands"}},{"node":{"categoryName":"Energy & Environment","iconId":"gas-pump","categorySlug":"energy-environment"}},{"node":{"categoryName":"Economy","iconId":"wallet","categorySlug":"economy"}},{"node":{"categoryName":"Education","iconId":"graduation-cap","categorySlug":"education"}},{"node":{"categoryName":"Government","iconId":"landmark","categorySlug":"government"}}]}}}